{
  "type": "Feature",
  "properties": {
    "gn:admin1_code":"11205436",
    "gn:asciiname":"North Hill Village",
    "gn:country_code":"AI",
    "gn:dem":36,
    "gn:feature_class":"P",
    "gn:feature_code":"PPLA",
    "gn:name":"North Hill Village",
    "gn:population":0,
    "gn:timezone":"America/Anguilla",
    "iso:country":"AI",
    "name:ell_x_preferred":[
        "\u0394\u03ae\u03bc\u03bf\u03c2 \u039d\u03bf\u03c1\u03b8 \u03a7\u03b9\u03bb"
    ],
    "name:fra_x_preferred":[
        "North Hill"
    ],
    "name:pol_x_preferred":[
        "North Hill"
    ],
    "wof:name":"North Hill Village",
    "wof:placetype":"locality"
},
  "geometry": {"coordinates":[-63.07847,18.20542],"type":"Point"}
}