{
  "type": "Feature",
  "properties": {
    "gn:admin1_code":"00",
    "gn:asciiname":"Mount Fortune",
    "gn:country_code":"AI",
    "gn:dem":5,
    "gn:feature_class":"P",
    "gn:feature_code":"PPL",
    "gn:name":"Mount Fortune",
    "gn:population":0,
    "gn:timezone":"America/Anguilla",
    "iso:country":"AI",
    "name:ceb_x_preferred":[
        "Mount Fortune"
    ],
    "wof:name":"Mount Fortune",
    "wof:placetype":"locality"
},
  "geometry": {"coordinates":[-62.99551999999999,18.24301],"type":"Point"}
}