{
  "type": "Feature",
  "properties": {
    "gn:admin1_code":"00",
    "gn:asciiname":"Crocus Hill",
    "gn:cc2":"AI",
    "gn:country_code":"AI",
    "gn:dem":61,
    "gn:feature_class":"P",
    "gn:feature_code":"PPL",
    "gn:name":"Crocus Hill",
    "gn:population":0,
    "gn:timezone":"America/Anguilla",
    "iso:country":"AI",
    "name:ara_x_preferred":[
        "\u062a\u0644 \u0643\u0631\u0648\u0643\u0633"
    ],
    "name:ben_x_preferred":[
        "\u0995\u09cd\u09b0\u09cb\u0995\u09be\u09b8 \u09b9\u09bf\u09b2"
    ],
    "name:ceb_x_preferred":[
        "Crocus Hill"
    ],
    "name:ces_x_preferred":[
        "Crocus Hill"
    ],
    "name:deu_x_preferred":[
        "Crocus Hill"
    ],
    "name:ell_x_preferred":[
        "\u039b\u03cc\u03c6\u03bf\u03c2 \u039a\u03c1\u03cc\u03ba\u03bf\u03c5\u03c2"
    ],
    "name:fas_x_preferred":[
        "\u062a\u067e\u0647 \u06a9\u0631\u0648\u06a9\u0648\u0633"
    ],
    "name:fra_x_preferred":[
        "Crocus Hill"
    ],
    "name:heb_x_preferred":[
        "\u05d2\u05d1\u05e2\u05ea \u05e7\u05e8\u05d5\u05e7\u05d5\u05e1"
    ],
    "name:hin_x_preferred":[
        "\u0915\u094d\u0930\u094b\u0915\u0938 \u0939\u093f\u0932"
    ],
    "name:hun_x_preferred":[
        "Crocus-hegy"
    ],
    "name:ind_x_preferred":[
        "Crocus Hill"
    ],
    "name:pol_x_preferred":[
        "Crocus Hill"
    ],
    "name:por_x_preferred":[
        "Crocus Hill"
    ],
    "name:rus_x_preferred":[
        "\u0433\u043e\u0440\u0430 \u041a\u0440\u043e\u043a\u0443\u0441-\u0425\u0438\u043b\u043b"
    ],
    "name:spa_x_preferred":[
        "Colina Crocus"
    ],
    "name:tur_x_preferred":[
        "Crocus Hill"
    ],
    "name:ukr_x_preferred":[
        "\u041a\u0440\u043e\u043a\u0443\u0441-\u0425\u0456\u043b\u043b"
    ],
    "name:und_x_variant":[
        "Saint Mary\u2019s"
    ],
    "name:urd_x_preferred":[
        "\u06a9\u0631\u0648\u06a9\u0633 \u06c1\u0644"
    ],
    "name:vie_x_preferred":[
        "N\u00fai Crocus"
    ],
    "name:zho_cn_x_preferred":[
        "\u514b\u7f57\u79d1\u65af\u5c71"
    ],
    "name:zho_tw_x_preferred":[
        "\u514b\u7f85\u514b\u65af\u5c71"
    ],
    "wof:name":"Crocus Hill",
    "wof:placetype":"locality"
},
  "geometry": {"coordinates":[-63.06393,18.2172],"type":"Point"}
}