{
  "type": "Feature",
  "properties": {
    "gn:admin1_code":"00",
    "gn:asciiname":"Crocus Hill",
    "gn:cc2":"AI",
    "gn:country_code":"AI",
    "gn:dem":61,
    "gn:feature_class":"P",
    "gn:feature_code":"PPL",
    "gn:name":"Crocus Hill",
    "gn:population":0,
    "gn:timezone":"America/Anguilla",
    "iso:country":"AI",
    "name:ceb_x_preferred":[
        "Crocus Hill"
    ],
    "name:ces_x_preferred":[
        "Crocus Hill"
    ],
    "name:fra_x_preferred":[
        "Crocus Hill"
    ],
    "name:pol_x_preferred":[
        "Crocus Hill"
    ],
    "name:und_x_variant":[
        "Saint Mary\u2019s"
    ],
    "wof:name":"Crocus Hill",
    "wof:placetype":"locality"
},
  "geometry": {"coordinates":[-63.06393000000001,18.2172],"type":"Point"}
}