{
  "type": "Feature",
  "properties": {
    "gn:admin1_code":"11205437",
    "gn:asciiname":"West End Village",
    "gn:country_code":"AI",
    "gn:dem":23,
    "gn:feature_class":"P",
    "gn:feature_code":"PPLA",
    "gn:name":"West End Village",
    "gn:population":0,
    "gn:timezone":"America/Anguilla",
    "iso:country":"AI",
    "name:fra_x_preferred":[
        "West End"
    ],
    "name:pol_x_preferred":[
        "West End"
    ],
    "wof:name":"West End Village",
    "wof:placetype":"locality"
},
  "geometry": {"coordinates":[-63.14941,18.17191],"type":"Point"}
}