{
  "type": "Feature",
  "properties": {
    "gn:country":"AI",
    "gn:fcode":"PPL",
    "gn:pop":942,
    "iso:country":"AI",
    "name:ara_x_preferred":[
        "\u0628\u0644\u0648\u064a\u0646\u063a \u0628\u0648\u064a\u0646\u062a"
    ],
    "name:ben_x_preferred":[
        "\u09ac\u09cd\u09b2\u09cb\u0987\u09af\u09bc\u09bf\u0982 \u09aa\u09af\u09bc\u09c7\u09a8\u09cd\u099f"
    ],
    "name:ceb_x_preferred":[
        "Blowing Point Village"
    ],
    "name:dan_x_preferred":[
        "Blowing Point"
    ],
    "name:deu_x_preferred":[
        "Blowing Point"
    ],
    "name:ell_x_preferred":[
        "\u0394\u03ae\u03bc\u03bf\u03c2 \u039c\u03c0\u03bb\u03bf\u03cc\u03c5\u03b9\u03bd\u03b3\u03ba \u03a0\u03cc\u03b9\u03bd\u03c4"
    ],
    "name:eng_x_preferred":[
        "Blowing Point"
    ],
    "name:fin_x_preferred":[
        "Blowing Point"
    ],
    "name:fra_x_preferred":[
        "Blowing Point"
    ],
    "name:guj_x_preferred":[
        "\u0aac\u0acd\u0ab2\u0acb\u0a87\u0a82\u0a97 \u0aaa\u0acb\u0a87\u0aa8\u0acd\u0a9f"
    ],
    "name:hin_x_preferred":[
        "\u092c\u094d\u0932\u094b\u0907\u0902\u0917 \u092a\u0949\u0907\u0902\u091f"
    ],
    "name:ind_x_preferred":[
        "Blowing Point"
    ],
    "name:ita_x_preferred":[
        "Blowing Point"
    ],
    "name:jpn_x_preferred":[
        "\u30d6\u30ed\u30fc\u30a4\u30f3\u30b0\u30fb\u30dd\u30a4\u30f3\u30c8"
    ],
    "name:kan_x_preferred":[
        "\u0caa\u0cbe\u0caf\u0cbf\u0c82\u0c9f\u0ccd \u0cac\u0cc0\u0cb3\u0cc1\u0cb5\u0cc1\u0ca6\u0cc1"
    ],
    "name:kor_x_preferred":[
        "\ube14\ub85c\uc789\ud3ec\uc778\ud2b8"
    ],
    "name:lav_x_preferred":[
        "Blovingpointa"
    ],
    "name:lit_x_preferred":[
        "Bloving Pointas"
    ],
    "name:mar_x_preferred":[
        "\u092c\u094d\u0932\u094b\u0935\u093f\u0902\u0917 \u092a\u0949\u0908\u0902\u091f"
    ],
    "name:msa_x_preferred":[
        "Blowing Point"
    ],
    "name:nld_x_preferred":[
        "Blowing Point"
    ],
    "name:nob_x_preferred":[
        "Blowing Point"
    ],
    "name:pol_x_preferred":[
        "Blowing Point"
    ],
    "name:por_x_preferred":[
        "Blowing Pont"
    ],
    "name:rus_x_preferred":[
        "\u0411\u043b\u043e\u0443\u0438\u043d\u0433-\u041f\u043e\u0439\u043d\u0442"
    ],
    "name:sin_x_preferred":[
        "\u0db6\u0dca\u0dbd\u0ddc\u0dc0\u0dd2\u0db1\u0dca\u0d9c\u0dca \u0db4\u0ddc\u0dba\u0dd2\u0db1\u0dca\u0da7\u0dca \u0d85\u0db1\u0dca\u0d9c\u0dd4\u0dba\u0dd2\u0dbd\u0dcf"
    ],
    "name:spa_x_preferred":[
        "Blowing Point"
    ],
    "name:swe_x_preferred":[
        "Blowing Point Village"
    ],
    "name:tam_x_preferred":[
        "\u0baa\u0bbf\u0bb2\u0bcb\u0bb5\u0bbf\u0b99\u0bcd  \u0baa\u0bbe\u0baf\u0bbf\u0ba3\u0bcd\u0b9f\u0bcd "
    ],
    "name:tel_x_preferred":[
        "\u0c2c\u0c4d\u0c32\u0c4b\u0c35\u0c3f\u0c02\u0c17\u0c4d \u0c2a\u0c3e\u0c2f\u0c3f\u0c02\u0c1f\u0c4d"
    ],
    "name:tha_x_preferred":[
        "\u0e40\u0e21\u0e37\u0e2d\u0e07\u0e44\u0e17\u0e08\u0e07"
    ],
    "name:tur_x_preferred":[
        "Blowing Point"
    ],
    "name:ukr_x_preferred":[
        "\u0411\u043b\u043e\u0432\u0456\u043d\u0433-\u041f\u043e\u0439\u043d\u0442"
    ],
    "name:urd_x_preferred":[
        "\u0628\u0644\u0648\u0626\u0646\u06af \u067e\u0648\u0627\u0626\u0646\u0679 "
    ],
    "name:vie_x_preferred":[
        "Blowing Point"
    ],
    "name:zho_x_preferred":[
        "\u5bf6\u69ae\u89d2"
    ],
    "qs:name":"Blowing Point Village",
    "qs:photos_9r":0,
    "qs:photos_sr":0,
    "qs:pop_sr":"2",
    "wd:wordcount":127,
    "wof:name":"Blowing Point Village",
    "wof:placetype":"locality",
    "wof:population":942
},
  "geometry": {"coordinates":[-63.08333,18.16667],"type":"Point"}
}