{
  "type": "Feature",
  "properties": {
    "gn:country":"AI",
    "gn:fcode":"PPL",
    "gn:pop":942,
    "iso:country":"AI",
    "qs:name":"Blowing Point Village",
    "qs:photos_9r":0,
    "qs:photos_sr":0,
    "qs:pop_sr":"2",
    "wd:wordcount":127,
    "wof:name":"Blowing Point Village",
    "wof:placetype":"locality",
    "wof:population":942
},
  "geometry": {"coordinates":[-63.08333,18.16667],"type":"Point"}
}