{
  "type": "Feature",
  "properties": {
    "gn:admin1_code":"00",
    "gn:asciiname":"Shoal Bay Village",
    "gn:cc2":"AI",
    "gn:country_code":"AI",
    "gn:dem":12,
    "gn:feature_class":"P",
    "gn:feature_code":"PPL",
    "gn:name":"Shoal Bay Village",
    "gn:population":0,
    "gn:timezone":"America/Anguilla",
    "iso:country":"AI",
    "name:und_x_variant":[
        "Shoal Village",
        "Shoal Bay Village"
    ],
    "wof:name":"Shoal Bay Village",
    "wof:placetype":"locality"
},
  "geometry": {"coordinates":[-63.02886,18.25385],"type":"Point"}
}