{
  "type": "Feature",
  "properties": {
    "gn:admin1_code":"11205439",
    "gn:asciiname":"The Quarter",
    "gn:country_code":"AI",
    "gn:dem":40,
    "gn:feature_class":"P",
    "gn:feature_code":"PPLA",
    "gn:name":"The Quarter",
    "gn:population":0,
    "gn:timezone":"America/Anguilla",
    "iso:country":"AI",
    "wof:name":"The Quarter",
    "wof:placetype":"locality"
},
  "geometry": {"coordinates":[-63.04178,18.20799],"type":"Point"}
}