{
  "type": "Feature",
  "properties": {
    "gn:admin1_code":"11205439",
    "gn:asciiname":"The Quarter",
    "gn:country_code":"AI",
    "gn:dem":40,
    "gn:feature_class":"P",
    "gn:feature_code":"PPLA",
    "gn:name":"The Quarter",
    "gn:population":0,
    "gn:timezone":"America/Anguilla",
    "iso:country":"AI",
    "name:ceb_x_preferred":[
        "The Quarter"
    ],
    "name:ell_x_preferred":[
        "\u0394\u03b5 \u039a\u03bf\u03c5\u03ac\u03c1\u03c4\u03b5\u03c1"
    ],
    "name:ell_x_variant":[
        "\u0394\u03ae\u03bc\u03bf\u03c2 \u0394\u03b5 \u039a\u03bf\u03c5\u03ce\u03c1\u03c4\u03b5\u03c1"
    ],
    "name:eng_x_preferred":[
        "The Quarter"
    ],
    "name:fas_x_preferred":[
        "\u06a9\u0648\u0627\u0631\u062a\u0631"
    ],
    "name:fra_x_preferred":[
        "The Quarter"
    ],
    "name:heb_x_preferred":[
        "\u05d4\u05e8\u05d5\u05d1\u05e2"
    ],
    "name:hin_x_preferred":[
        "\u091a\u094c\u0925\u093e\u0908"
    ],
    "name:hun_x_preferred":[
        "The Quarter"
    ],
    "name:ind_x_preferred":[
        "The Quarter"
    ],
    "name:ita_x_preferred":[
        "The Quarter"
    ],
    "name:jpn_x_preferred":[
        "\u30b6\u30fb\u30af\u30a9\u30fc\u30bf\u30fc"
    ],
    "name:kor_x_preferred":[
        "\ub354 \ucf70\ud130"
    ],
    "name:nld_x_preferred":[
        "The Quarter"
    ],
    "name:pol_x_preferred":[
        "The Quarter"
    ],
    "name:por_x_preferred":[
        "The Quarter"
    ],
    "name:rus_x_preferred":[
        "\u041a\u0443\u043e\u0440\u0442\u0435\u0440"
    ],
    "name:spa_x_preferred":[
        "The Quarter"
    ],
    "name:swe_x_preferred":[
        "The Quarter"
    ],
    "name:tur_x_preferred":[
        "The Quarter"
    ],
    "name:ukr_x_preferred":[
        "\u041a\u0432\u0430\u0440\u0442\u0435\u0440"
    ],
    "name:urd_x_preferred":[
        "\u062f\u06cc \u06a9\u0648\u0627\u0631\u0679\u0631"
    ],
    "name:vie_x_preferred":[
        "The Quarter"
    ],
    "name:zho_cn_x_preferred":[
        "\u5938\u7279"
    ],
    "name:zho_tw_x_preferred":[
        "\u5730\u57df"
    ],
    "wof:name":"The Quarter",
    "wof:placetype":"locality"
},
  "geometry": {"coordinates":[-63.04178,18.20799],"type":"Point"}
}