{
  "type": "Feature",
  "properties": {
    "gn:admin1_code":"00",
    "gn:asciiname":"Lower South Hill",
    "gn:country_code":"AI",
    "gn:dem":1,
    "gn:feature_class":"P",
    "gn:feature_code":"PPL",
    "gn:name":"Lower South Hill",
    "gn:population":0,
    "gn:timezone":"America/Anguilla",
    "iso:country":"AI",
    "wof:name":"Lower South Hill",
    "wof:placetype":"locality"
},
  "geometry": {"coordinates":[-63.10206,18.19209],"type":"Point"}
}